tesserag/__init__.py
tesserag/py.typed
tesserag-0.0.1.dist-info/METADATA
tesserag-0.0.1.dist-info/WHEEL
tesserag-0.0.1.dist-info/top_level.txt
tesserag-0.0.1.dist-info/RECORD
